{
  "works": [
    {
      "title": "[MG动画]首次尝试这种风格的（做的和史一样）",
      "videoId": "113933570605497",
      "bvid": "BV1NbF6ejELr",
      "cid": "28186182208",
      "link": "https://www.bilibili.com/video/BV1NbF6ejELr"
    },
    {
      "title": "TIRED OF PROBLEMS (Explicit)可视化",
      "videoId": "113653995017144",
      "bvid": "BV1t1q9YaEQy",
      "cid": "27347782531",
      "link": "https://www.bilibili.com/video/BV1t1q9YaEQy"
    },
    {
      "title": "[meme背景]一团糟",
      "videoId": "113496037590272",
      "bvid": "BV1YBUzYcE2D",
      "cid": "26801341428",
      "link": "https://www.bilibili.com/video/BV1YBUzYcE2D"
    }
  ]
}